{
  "frames": [
    {
      "filename": "building-shield-0.png",
      "frame": {
        "x": 0,
        "y": 0,
        "w": 1100,
        "h": 1100
      },
      "rotated": false,
      "trimmed": false,
      "spriteSourceSize": {
        "x": 0,
        "y": 0,
        "w": 1100,
        "h": 1100
      },
      "sourceSize": {
        "w": 1100,
        "h": 1100
      },
      "pivot": {
        "x": 0.5,
        "y": 0.5
      }
    },
    {
      "filename": "building-shield-1.png",
      "frame": {
        "x": 0,
        "y": 1100,
        "w": 1100,
        "h": 1100
      },
      "rotated": false,
      "trimmed": false,
      "spriteSourceSize": {
        "x": 0,
        "y": 0,
        "w": 1100,
        "h": 1100
      },
      "sourceSize": {
        "w": 1100,
        "h": 1100
      },
      "pivot": {
        "x": 0.5,
        "y": 0.5
      }
    },
    {
      "filename": "building-shield-2.png",
      "frame": {
        "x": 1100,
        "y": 0,
        "w": 1100,
        "h": 1100
      },
      "rotated": false,
      "trimmed": false,
      "spriteSourceSize": {
        "x": 0,
        "y": 0,
        "w": 1100,
        "h": 1100
      },
      "sourceSize": {
        "w": 1100,
        "h": 1100
      },
      "pivot": {
        "x": 0.5,
        "y": 0.5
      }
    },
    {
      "filename": "destroying-shield-0.png",
      "frame": {
        "x": 0,
        "y": 2200,
        "w": 1100,
        "h": 1100
      },
      "rotated": false,
      "trimmed": false,
      "spriteSourceSize": {
        "x": 0,
        "y": 0,
        "w": 1100,
        "h": 1100
      },
      "sourceSize": {
        "w": 1100,
        "h": 1100
      },
      "pivot": {
        "x": 0.5,
        "y": 0.5
      }
    },
    {
      "filename": "destroying-shield-1.png",
      "frame": {
        "x": 1100,
        "y": 1100,
        "w": 1100,
        "h": 1100
      },
      "rotated": false,
      "trimmed": false,
      "spriteSourceSize": {
        "x": 0,
        "y": 0,
        "w": 1100,
        "h": 1100
      },
      "sourceSize": {
        "w": 1100,
        "h": 1100
      },
      "pivot": {
        "x": 0.5,
        "y": 0.5
      }
    },
    {
      "filename": "destroying-shield-2.png",
      "frame": {
        "x": 2200,
        "y": 0,
        "w": 1100,
        "h": 1100
      },
      "rotated": false,
      "trimmed": false,
      "spriteSourceSize": {
        "x": 0,
        "y": 0,
        "w": 1100,
        "h": 1100
      },
      "sourceSize": {
        "w": 1100,
        "h": 1100
      },
      "pivot": {
        "x": 0.5,
        "y": 0.5
      }
    },
    {
      "filename": "shield-0.png",
      "frame": {
        "x": 0,
        "y": 3300,
        "w": 1100,
        "h": 1100
      },
      "rotated": false,
      "trimmed": false,
      "spriteSourceSize": {
        "x": 0,
        "y": 0,
        "w": 1100,
        "h": 1100
      },
      "sourceSize": {
        "w": 1100,
        "h": 1100
      },
      "pivot": {
        "x": 0.5,
        "y": 0.5
      }
    },
    {
      "filename": "shield-1.png",
      "frame": {
        "x": 1100,
        "y": 2200,
        "w": 1100,
        "h": 1100
      },
      "rotated": false,
      "trimmed": false,
      "spriteSourceSize": {
        "x": 0,
        "y": 0,
        "w": 1100,
        "h": 1100
      },
      "sourceSize": {
        "w": 1100,
        "h": 1100
      },
      "pivot": {
        "x": 0.5,
        "y": 0.5
      }
    },
    {
      "filename": "shield-2.png",
      "frame": {
        "x": 2200,
        "y": 1100,
        "w": 1100,
        "h": 1100
      },
      "rotated": false,
      "trimmed": false,
      "spriteSourceSize": {
        "x": 0,
        "y": 0,
        "w": 1100,
        "h": 1100
      },
      "sourceSize": {
        "w": 1100,
        "h": 1100
      },
      "pivot": {
        "x": 0.5,
        "y": 0.5
      }
    },
    {
      "filename": "shield-3.png",
      "frame": {
        "x": 3300,
        "y": 0,
        "w": 1100,
        "h": 1100
      },
      "rotated": false,
      "trimmed": false,
      "spriteSourceSize": {
        "x": 0,
        "y": 0,
        "w": 1100,
        "h": 1100
      },
      "sourceSize": {
        "w": 1100,
        "h": 1100
      },
      "pivot": {
        "x": 0.5,
        "y": 0.5
      }
    }
  ],
  "meta": {
    "app": "http://free-tex-packer.com",
    "version": "0.6.7",
    "image": "Alzareth_Shield.png",
    "format": "RGBA8888",
    "size": {
      "w": 4400,
      "h": 4400
    },
    "scale": 1
  }
}